boto_creds_path/__init__.py
botocredspath-0.0.1.dist-info/METADATA
botocredspath-0.0.1.dist-info/WHEEL
botocredspath-0.0.1.dist-info/top_level.txt
botocredspath-0.0.1.dist-info/RECORD
