Metadata-Version: 2.1
Name: botocredspath
Version: 0.0.1
Summary: enables you to directly set boto3 aws folder path.
Home-page: UNKNOWN
Author: Health Union Data Team
Author-email: data@health-union.com
License: UNKNOWN
Platform: UNKNOWN
Classifier: Development Status :: 3 - Alpha
Classifier: License :: OSI Approved :: MIT License
Classifier: Operating System :: OS Independent
Requires-Python: >=3.7
